tizbrain/__init__.py
tizbrain-0.0.1.dist-info/METADATA
tizbrain-0.0.1.dist-info/WHEEL
tizbrain-0.0.1.dist-info/RECORD
