Metadata-Version: 2.4
Name: tizbrain
Version: 0.0.1
Summary: TizBrain SDK for Python
Project-URL: Homepage, https://tizbrain.com
Author-email: TizBrain <contact@tizbrain.com>
License: MIT
Keywords: agents,ai,copilot,openseespy,tizbrain
Classifier: Development Status :: 2 - Pre-Alpha
Classifier: Intended Audience :: Developers
Classifier: License :: OSI Approved :: MIT License
Classifier: Programming Language :: Python :: 3
Classifier: Programming Language :: Python :: 3 :: Only
Classifier: Programming Language :: Python :: 3.8
Classifier: Programming Language :: Python :: 3.9
Classifier: Programming Language :: Python :: 3.10
Classifier: Programming Language :: Python :: 3.11
Classifier: Programming Language :: Python :: 3.12
Classifier: Programming Language :: Python :: 3.13
Classifier: Topic :: Software Development :: Libraries
Requires-Python: >=3.8
